restricted_fields/__init__.py
restricted_fields/mixins.py
drf_restricted_fields-0.0.1.dist-info/AUTHORS.rst
drf_restricted_fields-0.0.1.dist-info/LICENSE
drf_restricted_fields-0.0.1.dist-info/METADATA
drf_restricted_fields-0.0.1.dist-info/WHEEL
drf_restricted_fields-0.0.1.dist-info/top_level.txt
drf_restricted_fields-0.0.1.dist-info/RECORD
